qrdm/__init__.py
qrdm/exceptions.py
qrdm/models.py
qrdm/backend/__init__.py
qrdm/backend/config.py
qrdm/backend/main.py
qrdm/backend/routers/__init__.py
qrdm/backend/routers/qr.py
qrdm/qr/__init__.py
qrdm/qr/_const.py
qrdm/qr/decode.py
qrdm/qr/encode.py
qrdm/qr/pdf_writer.py
qrdm/qr/data/__init__.py
qrdm/qr/data/qr_capacity.csv
qrdm/qr/data/qrdm_logo_red.png
qrdm/qr/protobuf/__init__.py
qrdm/qr/protobuf/qrdm.proto
qrdm/qr/protobuf/qrdm_pb2.py
qrdm/qr/protobuf/qrdm_pb2.pyi
qrdm-2.1.0.dist-info/LICENSE.txt
qrdm-2.1.0.dist-info/METADATA
qrdm-2.1.0.dist-info/WHEEL
qrdm-2.1.0.dist-info/top_level.txt
qrdm-2.1.0.dist-info/RECORD
