Metadata-Version: 2.1
Name: qrdm
Version: 2.1.0
Summary: QR Data Manager
Author: MIT Lincoln Laboratory
Author-email: "Cuyler D. O'Brien" <cuyler.obrien@ll.mit.edu>, "Eric A. Quintero" <Eric.Quintero@ll.mit.edu>, Tod Shannon <tod@ll.mit.edu>, "Michael J. Snyder" <michael.snyder@ll.mit.edu>
License: MIT License
Project-URL: Documentation, https://mit-ll.github.io/qrdm
Project-URL: Repository, https://github.com/mit-ll/qrdm
Keywords: QR,QR code
Classifier: Development Status :: 4 - Beta
Classifier: License :: OSI Approved :: MIT License
Classifier: Programming Language :: Python :: 3
Classifier: Programming Language :: Python :: 3.9
Classifier: Programming Language :: Python :: 3.10
Classifier: Programming Language :: Python :: 3.11
Classifier: Programming Language :: Python :: 3.12
Requires-Python: >=3.9
License-File: LICENSE.txt
Requires-Dist: charset-normalizer ~=3.2
Requires-Dist: Pillow ~=10.1
Requires-Dist: protobuf >=4.22
Requires-Dist: pydantic ~=2.2
Requires-Dist: pydantic-settings
Requires-Dist: PyMuPDF ~=1.22
Requires-Dist: pyzbar ~=0.1.8
Requires-Dist: qrcode ~=7.3
Requires-Dist: reedsolo ~=1.7.0
Requires-Dist: reportlab ~=4.0
Requires-Dist: structlog ~=23.0
Requires-Dist: svglib ~=1.5
Provides-Extra: backend
Requires-Dist: fastapi ==0.109 ; extra == 'backend'
Requires-Dist: python-multipart ~=0.0.6 ; extra == 'backend'
Requires-Dist: starlette[full] ; extra == 'backend'
Requires-Dist: uvicorn[standard] ; extra == 'backend'
Provides-Extra: dev
Requires-Dist: qrdm[backend,doc,frontend,test] ; extra == 'dev'
Requires-Dist: black ; extra == 'dev'
Requires-Dist: ruff ; extra == 'dev'
Requires-Dist: tox ~=4.0 ; extra == 'dev'
Requires-Dist: build ; extra == 'dev'
Requires-Dist: twine ; extra == 'dev'
Provides-Extra: doc
Requires-Dist: furo ; extra == 'doc'
Requires-Dist: myst-parser ; extra == 'doc'
Requires-Dist: sphinx ~=7.2.0 ; extra == 'doc'
Provides-Extra: frontend
Requires-Dist: streamlit ~=1.28 ; extra == 'frontend'
Provides-Extra: test
Requires-Dist: pytest ~=7.0 ; extra == 'test'
Requires-Dist: coverage[toml] ; extra == 'test'
